dora_mediapipe/__init__.py
dora_mediapipe/__main__.py
dora_mediapipe/main.py
dora_mediapipe-0.0.0.dist-info/METADATA
dora_mediapipe-0.0.0.dist-info/WHEEL
dora_mediapipe-0.0.0.dist-info/entry_points.txt
dora_mediapipe-0.0.0.dist-info/top_level.txt
dora_mediapipe-0.0.0.dist-info/RECORD
