Metadata-Version: 2.4
Name: dora-mediapipe
Version: 0.0.0
Summary: dora-mediapipe
Author-email: Your Name <email@email.com>
License: MIT
Requires-Python: >=3.8
Requires-Dist: dora-rs>=0.3.9
Requires-Dist: mediapipe>=0.10.14
